LICENSE
MANIFEST.in
README.rst
example.py
setup.py
./ziptax/__init__.py
python_ziptax.egg-info/PKG-INFO
python_ziptax.egg-info/SOURCES.txt
python_ziptax.egg-info/dependency_links.txt
python_ziptax.egg-info/not-zip-safe
python_ziptax.egg-info/top_level.txt