Metadata-Version: 1.0
Name: python-ziptax
Version: 1.0.2
Summary: Library for zip-tax.com API service
Home-page: https://github.com/xstudios/python-ziptax
Author: X Studios Inc.
Author-email: nwhiting@xstudiosinc.com
License: Copyright 2010-12 X Studios Inc
